omega_aidas/__init__.py
omega_aidas/core/__init__.py
omega_aidas/core/api.py
omega_aidas/core/impl.py
omega_aidas/core/ops.py
omega_aidas-1.0.7.dist-info/METADATA
omega_aidas-1.0.7.dist-info/WHEEL
omega_aidas-1.0.7.dist-info/top_level.txt
omega_aidas-1.0.7.dist-info/RECORD
